basedai/__init__.py
basedai/basednode.py
basedai/brainport.py
basedai/brainrequester.py
basedai/brainresponder.py
basedai/broadcast.py
basedai/btlogging.py
basedai/chain_data.py
basedai/cli.py
basedai/config.py
basedai/errors.py
basedai/keyfile.py
basedai/stem.py
basedai/stream.py
basedai/tensor.py
basedai/threadpool.py
basedai/types.py
basedai/wallet.py
basedai/commands/__init__.py
basedai/commands/brainstore.py
basedai/commands/core.py
basedai/commands/delegates.py
basedai/commands/fhe.py
basedai/commands/gigabrain.py
basedai/commands/identity.py
basedai/commands/inspect.py
basedai/commands/list.py
basedai/commands/memorize.py
basedai/commands/misc.py
basedai/commands/network.py
basedai/commands/overview.py
basedai/commands/stake.py
basedai/commands/stem.py
basedai/commands/transfer.py
basedai/commands/unstake.py
basedai/commands/utils.py
basedai/commands/wallets.py
basedai/extrinsics/__init__.py
basedai/extrinsics/delegation.py
basedai/extrinsics/gigabrains.py
basedai/extrinsics/log_utilities.py
basedai/extrinsics/mainnet.py
basedai/extrinsics/network.py
basedai/extrinsics/registration.py
basedai/extrinsics/root.py
basedai/extrinsics/serving.py
basedai/extrinsics/set_weights.py
basedai/extrinsics/staking.py
basedai/extrinsics/transfer.py
basedai/extrinsics/unstaking.py
basedai/utils/__init__.py
basedai/utils/_register_cuda.py
basedai/utils/balance.py
basedai/utils/formatting.py
basedai/utils/networking.py
basedai/utils/registration.py
basedai/utils/test_utils.py
basedai/utils/wallet_utils.py
basedai/utils/weight_utils.py
basedai-1.1.2.data/scripts/basedcli
basedai-1.1.2.dist-info/LICENSE
basedai-1.1.2.dist-info/METADATA
basedai-1.1.2.dist-info/WHEEL
basedai-1.1.2.dist-info/top_level.txt
basedai-1.1.2.dist-info/RECORD
