Metadata-Version: 2.1
Name: basedai
Version: 1.1.2
Summary: basedai
Home-page: https://github.com/getbasedai/basedai
Author: getbased.ai
Author-email: 
License: MIT
Classifier: Development Status :: 3 - Alpha
Classifier: Intended Audience :: Developers
Classifier: Topic :: Software Development :: Build Tools
Classifier: License :: OSI Approved :: MIT License
Classifier: Programming Language :: Python :: 3 :: Only
Classifier: Programming Language :: Python :: 3.8
Classifier: Programming Language :: Python :: 3.9
Classifier: Programming Language :: Python :: 3.10
Classifier: Topic :: Scientific/Engineering
Classifier: Topic :: Scientific/Engineering :: Mathematics
Classifier: Topic :: Scientific/Engineering :: Artificial Intelligence
Classifier: Topic :: Scientific/Engineering :: Information Analysis
Classifier: Topic :: Scientific/Engineering :: Visualization
Classifier: Topic :: Scientific/Engineering :: Bio-Informatics
Classifier: Topic :: Scientific/Engineering :: Medical Science Apps.
Classifier: Topic :: Scientific/Engineering :: Physics
Classifier: Topic :: Software Development
Classifier: Topic :: Software Development :: Libraries
Classifier: Topic :: Software Development :: Libraries :: Python Modules
Requires-Python: >=3.8
License-File: LICENSE
Requires-Dist: aiohttp==3.9.0
Requires-Dist: ansible==6.7.0
Requires-Dist: ansible-vault==2.1.0
Requires-Dist: backoff
Requires-Dist: black==23.7.0
Requires-Dist: cryptography==41.0.3
Requires-Dist: ddt==1.6.0
Requires-Dist: fuzzywuzzy>=0.18.0
Requires-Dist: fastapi==0.99.1
Requires-Dist: loguru==0.7.0
Requires-Dist: munch==2.5.0
Requires-Dist: netaddr
Requires-Dist: numpy
Requires-Dist: msgpack-numpy-opentensor==0.5.0
Requires-Dist: nest-asyncio
Requires-Dist: pycryptodome<4.0.0,>=3.18.0
Requires-Dist: pyyaml
Requires-Dist: password-strength
Requires-Dist: pydantic!=1.8,!=1.8.1,<2.0.0,>=1.7.4
Requires-Dist: PyNaCl<=1.5.0,>=1.3.0
Requires-Dist: pytest-asyncio
Requires-Dist: python-Levenshtein
Requires-Dist: pytest
Requires-Dist: retry
Requires-Dist: requests
Requires-Dist: rich
Requires-Dist: scalecodec==1.2.7
Requires-Dist: shtab==1.6.5
Requires-Dist: substrate-interface==1.5.2
Requires-Dist: termcolor
Requires-Dist: torch>=1.13.1
Requires-Dist: tqdm
Requires-Dist: uvicorn==0.22.0
Requires-Dist: wheel
Requires-Dist: tenseal
Requires-Dist: phe
Requires-Dist: ollama
Requires-Dist: websockets
Provides-Extra: dev
Requires-Dist: pytest==7.2.0; extra == "dev"
Requires-Dist: pytest-split==0.8.0; extra == "dev"
Requires-Dist: pytest-xdist==3.0.2; extra == "dev"
Requires-Dist: pytest-rerunfailures==10.2; extra == "dev"
Requires-Dist: coveralls==3.3.1; extra == "dev"
Requires-Dist: pytest-cov==4.0.0; extra == "dev"
Requires-Dist: ddt==1.6.0; extra == "dev"
Requires-Dist: hypothesis==6.81.1; extra == "dev"
